apopy/__init__.py
apopy-0.1.6.dist-info/METADATA
apopy-0.1.6.dist-info/WHEEL
apopy-0.1.6.dist-info/licenses/LICENSE
apopy-0.1.6.dist-info/RECORD
