Metadata-Version: 2.3
Name: apopy
Version: 0.1.6
Summary: Simple Apollo Config Client for Python.
Maintainer-email: ringsaturn <ringsaturn.me@gmail.com>
License-Expression: MIT
License-File: LICENSE
Requires-Python: >=3.9
Requires-Dist: httpx[socks]>=0.27.2
